{
    "05-08": {
        "중식": {
            "운영시간": ["11:00", "13:45"],
            "메뉴": [{
                "구분": "뚝배기",
                "가격": 5000,
                "상세메뉴": [
                    "참치김치찌개&당면사리", "쌀밥", "김말이데리강정", "야채계란찜", "배추김치"
                ]
            }, {
                "구분": "카츠카츠A",
                "가격": 6000,
                "상세메뉴": [
                    "순살치킨카츠&요거트드레싱", "추가밥", "맑은우동국물", "푸실리토마토샐러드", "토마토식빵&사과잼", "단무지", "배추김치"
                ]
            }]
        },
        "스낵바/셀프라면": {
            "운영시간": ["13:30", "15:00"],
            "메누": [{
                "구분": "뚝배기",
                "가격": 5000,
                "상세메뉴": [
                    "참치김치찌개&당면사리",
                    "쌀밥",
                    "김말이데리강정",
                    "야채계란찜",
                    "배추김치"
                ]
            }]
        }
    }
}

['등심돈카츠',
'추가밥',
'맑은우동국물',
'그린샐러드&드레싱',
'토스트식빵&사과잼',
'단무지',
'배추김치']